af_remote_html_runtime_manager/__init__.py
af_remote_html_runtime_manager/api_client.py
af_remote_html_runtime_manager/configuration.py
af_remote_html_runtime_manager/rest.py
af_remote_html_runtime_manager/api/__init__.py
af_remote_html_runtime_manager/api/arista_flow_service_api.py
af_remote_html_runtime_manager/api/as_remote_iterator_api.py
af_remote_html_runtime_manager/api/default_api.py
af_remote_html_runtime_manager/api/execution_control_manager_api.py
af_remote_html_runtime_manager/api/ns_remote_iterator_api.py
af_remote_html_runtime_manager/api/runtime_manager_api.py
af_remote_html_runtime_manager/api/synchronous_activity_starting_api.py
af_remote_html_runtime_manager/models/__init__.py
af_remote_html_runtime_manager/models/abort_service_exception.py
af_remote_html_runtime_manager/models/abort_transaction_exception.py
af_remote_html_runtime_manager/models/accessed_process_model_parameter.py
af_remote_html_runtime_manager/models/activity_callback_data.py
af_remote_html_runtime_manager/models/activity_configuration.py
af_remote_html_runtime_manager/models/activity_data_container.py
af_remote_html_runtime_manager/models/activity_exec_data.py
af_remote_html_runtime_manager/models/activity_exec_failed_data.py
af_remote_html_runtime_manager/models/activity_exec_resumed_data.py
af_remote_html_runtime_manager/models/activity_exec_resumed_rest_data.py
af_remote_html_runtime_manager/models/activity_exec_resumed_sse_data.py
af_remote_html_runtime_manager/models/activity_exec_signalled_data.py
af_remote_html_runtime_manager/models/activity_exec_suspended_data.py
af_remote_html_runtime_manager/models/activity_instance.py
af_remote_html_runtime_manager/models/activity_rest_callback_data.py
af_remote_html_runtime_manager/models/activity_sse_callback_data.py
af_remote_html_runtime_manager/models/activity_state.py
af_remote_html_runtime_manager/models/activity_with_act_state.py
af_remote_html_runtime_manager/models/activity_with_node_state.py
af_remote_html_runtime_manager-4.0.3.dist-info/LICENSE
af_remote_html_runtime_manager-4.0.3.dist-info/METADATA
af_remote_html_runtime_manager-4.0.3.dist-info/WHEEL
af_remote_html_runtime_manager-4.0.3.dist-info/top_level.txt
af_remote_html_runtime_manager-4.0.3.dist-info/RECORD
